MANIFEST.in
README.rst
setup.py
google/__init__.py
google/pubsub/__init__.py
google/pubsub/v1/__init__.py
google/pubsub/v1/pubsub_pb2.py
grpc_google_pubsub_v1.egg-info/PKG-INFO
grpc_google_pubsub_v1.egg-info/SOURCES.txt
grpc_google_pubsub_v1.egg-info/dependency_links.txt
grpc_google_pubsub_v1.egg-info/namespace_packages.txt
grpc_google_pubsub_v1.egg-info/requires.txt
grpc_google_pubsub_v1.egg-info/top_level.txt